y2mate/__init__.py
y2mate/client.py
y2mate/constants.py
y2mate/models.py
y2mate-1.0.0.dist-info/METADATA
y2mate-1.0.0.dist-info/WHEEL
y2mate-1.0.0.dist-info/top_level.txt
y2mate-1.0.0.dist-info/RECORD
