Metadata-Version: 2.1
Name: y2mate
Version: 1.0.0
Summary: An unofficial API wrapper for Y2Mate.com
Home-page: https://github.com/zrekryu/y2mate
Author: Zrekryu
Author-email: zrekryu@gmail.com
Keywords: y2mate,y2mate-api,youtube
Classifier: Development Status :: 5 - Production/Stable
Classifier: Intended Audience :: Developers
Classifier: License :: OSI Approved :: The Unlicense (Unlicense)
Classifier: Operating System :: OS Independent
Classifier: Programming Language :: Python
Classifier: Programming Language :: Python :: 3
Classifier: Topic :: Software Development :: Libraries :: Python Modules
Classifier: Topic :: Internet :: WWW/HTTP
Classifier: Topic :: Utilities
Requires-Dist: httpx
